README.md
setup.py
Topsis_chirag_102303483.egg-info/PKG-INFO
Topsis_chirag_102303483.egg-info/SOURCES.txt
Topsis_chirag_102303483.egg-info/dependency_links.txt
Topsis_chirag_102303483.egg-info/entry_points.txt
Topsis_chirag_102303483.egg-info/requires.txt
Topsis_chirag_102303483.egg-info/top_level.txt
topsis/__init__.py
topsis/topsis.py