Metadata-Version: 2.4
Name: Topsis-chirag-102303483
Version: 1.0.3
Summary: TOPSIS implementation using Python
Author: Chirag Gupta
Requires-Python: >=3.7
Requires-Dist: pandas
Requires-Dist: numpy
Dynamic: author
Dynamic: description
Dynamic: description-content-type
Dynamic: requires-dist
Dynamic: requires-python
Dynamic: summary
